alumathgroup_25/__init__.py
alumathgroup_25/main.py
alumathgroup_25/test_matrix1.py
alumath_linear_algebra-1.0.0.dist-info/METADATA
alumath_linear_algebra-1.0.0.dist-info/WHEEL
alumath_linear_algebra-1.0.0.dist-info/top_level.txt
alumath_linear_algebra-1.0.0.dist-info/RECORD
