Metadata-Version: 2.1
Name: alumath_linear_algebra
Version: 1.0.0
Summary: A friendly matrix multiplication package by Kabango Mathias.
Author: Kabango Mathias, Orpheus Manga, Reine Mizero
Author-email: m.kabango@alustudent.com
Requires-Python: >=3.6
